fuel_efficency/__init__.py
fuel_efficency/algorithms/__init__.py
fuel_efficency/algorithms/a_star.py
fuel_efficency/algorithms/context.py
fuel_efficency/algorithms/dijkstra.py
fuel_efficency/algorithms/path_finding.py
fuel_efficency/entities/__init__.py
fuel_efficency/entities/down_hill.py
fuel_efficency/entities/node.py
fuel_efficency/entities/plateau.py
fuel_efficency/entities/position.py
fuel_efficency/entities/up_hill.py
fuel_efficency/entities/valley.py
bees_ml_path_challenge_skeleton-1.0.0.dist-info/METADATA
bees_ml_path_challenge_skeleton-1.0.0.dist-info/WHEEL
bees_ml_path_challenge_skeleton-1.0.0.dist-info/RECORD
