Metadata-Version: 2.3
Name: bees_ml_path_challenge-skeleton
Version: 1.0.0
Project-URL: Homepage, https://github.com/rodrigoruiz/bees_ml_path_challenge-skeleton
Classifier: License :: OSI Approved :: MIT License
Classifier: Operating System :: OS Independent
Classifier: Programming Language :: Python :: 3
Requires-Python: >=3.10
